arduinoiot/__init__.py
iotrasp1-2.0.dist-info/METADATA
iotrasp1-2.0.dist-info/WHEEL
iotrasp1-2.0.dist-info/top_level.txt
iotrasp1-2.0.dist-info/RECORD
